mllp_https_gui/__init__.py
mllp_https_gui/first_window.py
mllp_https_gui/gui.py
mllp_https_gui/https2mllp_config_window.py
mllp_https_gui/loading_window.py
mllp_https_gui/log_folder_monitor.py
mllp_https_gui/main.py
mllp_https_gui/mllp2https_config_window.py
mllp_https_gui/version.py
mllp_https_gui/doc/icon.ico
mllp_https_gui/doc/logo.ico
mllp_https_gui/doc/logo.png
mllp_https_gui/doc/logo_https2mllp.png
mllp_https_gui/doc/logo_mllp2https.png
mllp_https_gui-0.0.31.dist-info/LICENSE.txt
mllp_https_gui-0.0.31.dist-info/METADATA
mllp_https_gui-0.0.31.dist-info/WHEEL
mllp_https_gui-0.0.31.dist-info/entry_points.txt
mllp_https_gui-0.0.31.dist-info/top_level.txt
mllp_https_gui-0.0.31.dist-info/RECORD
