Metadata-Version: 2.1
Name: mllp-https-gui
Version: 0.0.31
Summary: GUI to install and configure mllp-https
Home-page: https://github.com/tiagoepr/mllp-https
Author: Tiago Rodrigues/SECTRA Iberia
Author-email: Tiago.Rodrigues@sectra.com
License: MIT
Project-URL: Issues, https://github.com/tiagoepr/mllp-https/issues
Classifier: License :: OSI Approved :: MIT License
Classifier: Operating System :: OS Independent
Classifier: Programming Language :: Python
Classifier: Programming Language :: Python :: 3
License-File: LICENSE.txt
Requires-Dist: mllp-https
Requires-Dist: pysimplegui
